chitti/__init__.py
chitti/color_text.py
chitti/list_to_dic.py
chitti/print.py
chitti/sklearn_utilities.py
chitti/train_test_split.py
chitti/nlp/__init__.py
chitti/nlp/clean_text.py
chitti/nlp/download_pretrained_vectors.py
chitti/nlp/pretrained_vectors.py
tests/__init__.py
tests/test.py
chitti-0.2.7.dist-info/LICENSE
chitti-0.2.7.dist-info/METADATA
chitti-0.2.7.dist-info/WHEEL
chitti-0.2.7.dist-info/top_level.txt
chitti-0.2.7.dist-info/RECORD
